{
	"create_time": "2021-06-28T06:50:42.905Z",
	"display_name": "Ecommerce Spec",
	"name": "workspaces/1iSatLbk9xhE4qBXXzdWajZ3HVF/tracking-plans/tp_1uZB4vCgfpXnpDv2Yqfgva5FiIk",
	"rules": {
		"events": [
			{
				"description": "This event is triggered whenever a user completes a order on your website or app",
				"id": "ev_1uZIYdFmncTAAET6hdSzQkfz2Qq",
				"name": "Order Purchased",
				"rules": {
					"$schema": "http://json-schema.org/draft-04/schema#",
					"properties": {
						"context": {
						},
						"properties": {
							"properties": {
								"category": {
									"type": "string"
								},
								"list_id": {
									"type": "string"
								},
								"products": {
									"items": {
										"properties": {
											"brand": {
												"type": "string"
											},
											"category": {
												"type": "string"
											},
											"coupon": {
												"type": "string"
											},
											"image_url": {
												"type": "string"
											},
											"name": {
												"type": "string"
											},
											"position": {
												"type": "number"
											},
											"price": {
												"type": "number"
											},
											"product_id": {
												"type": "string"
											},
											"quantity": {
												"type": "number"
											},
											"sku": {
												"type": "string"
											},
											"url": {
												"type": "string"
											},
											"variant": {
												"type": "string"
											}
										},
										"required": [
											"product_id",
											"sku",
											"category",
											"name",
											"brand",
											"variant",
											"price",
											"quantity",
											"position",
											"coupon"
										],
										"type": "object"
									},
									"type": "array"
								}
							},
							"type": "object"
						}
					},
					"type": "object"
				},
				"version": "1-0-0"
			},
			{
				"description": "This events is triggered whenever a visitor views a list or category of products on your website or app",
				"id": "ev_1uZB4pTVXgTelgNz7nYSuR4RBsr",
				"name": "Product List Viewed",
				"rules": {
					"$schema": "http://json-schema.org/draft-04/schema#",
					"properties": {
						"context": {
						},
						"properties": {
							"properties": {
								"category": {
									"type": "string"
								},
								"list_id": {
									"type": "string"
								},
								"products": {
									"items": {
										"properties": {
											"brand": {
												"type": "string"
											},
											"category": {
												"type": "string"
											},
											"coupon": {
												"type": "string"
											},
											"image_url": {
												"type": "string"
											},
											"name": {
												"type": "string"
											},
											"position": {
												"type": "number"
											},
											"price": {
												"type": "number"
											},
											"product_id": {
												"type": "string"
											},
											"quantity": {
												"type": "number"
											},
											"sku": {
												"type": "string"
											},
											"url": {
												"type": "string"
											},
											"variant": {
												"type": "string"
											}
										},
										"required": [
											"product_id",
											"sku",
											"category",
											"name",
											"brand",
											"variant",
											"price",
											"quantity",
											"position",
											"coupon"
										],
										"type": "object"
									},
									"type": "array"
								}
							},
							"type": "object"
						}
					},
					"type": "object"
				},
				"version": "3-0-0"
			},
			{
				"description": "This Event indicates that a product has been added to cart and its details",
				"id": "ev_1wwUhOV2VbYc3eXcCJc65KQxenq",
				"name": "Product Added",
				"rules": {
					"$schema": "http://json-schema.org/draft-06/schema#",
					"properties": {
						"context": {
						},
						"properties": {
							"properties": {
								"category": {
									"type": "string"
								},
								"details": {
									"properties": {
										"brand": {
											"type": "string"
										},
										"category": {
											"type": "string"
										},
										"coupon": {
											"type": "string"
										},
										"image_url": {
											"type": "string"
										},
										"name": {
											"type": "string"
										},
										"position": {
											"type": "number"
										},
										"price": {
											"type": "number"
										},
										"product_id": {
											"type": "string"
										},
										"quantity": {
											"type": "number"
										},
										"sku": {
											"type": "string"
										},
										"url": {
											"type": "string"
										},
										"variant": {
											"type": "string"
										}
									},
									"required": [
										"product_id",
										"sku",
										"category",
										"name",
										"price",
										"position",
										"url",
										"image_url"
									],
									"type": "object"
								},
								"list_id": {
									"type": "string"
								}
							},
							"required": [
								"list_id",
								"category"
							],
							"type": "object"
						},
						"traits": {
						}
					},
					"type": "object"
				},
				"version": "3-0-0"
			}
		]
	},
	"update_time": "2022-03-22T07:52:25.809Z",
	"version": 11
}